README.txt
setup.py
central_lock/__init__.py
central_lock/central_lock.py
central_lock.egg-info/PKG-INFO
central_lock.egg-info/SOURCES.txt
central_lock.egg-info/dependency_links.txt
central_lock.egg-info/requires.txt
central_lock.egg-info/top_level.txt