Metadata-Version: 1.0
Name: central-lock
Version: 1.0.2
Summary: A central lock for distribute applications
Home-page: https://github.com/zhaofl2015/central_lock
Author: fanglei.zhao
Author-email: 281146581@qq.com
License: MIT
Platform: UNKNOWN
